alibaba_cloud_ops_mcp_server/__init__.py
alibaba_cloud_ops_mcp_server/__main__.py
alibaba_cloud_ops_mcp_server/config.py
alibaba_cloud_ops_mcp_server/server.py
alibaba_cloud_ops_mcp_server/settings.py
alibaba_cloud_ops_mcp_server/alibabacloud/__init__.py
alibaba_cloud_ops_mcp_server/alibabacloud/api_meta_client.py
alibaba_cloud_ops_mcp_server/alibabacloud/exception.py
alibaba_cloud_ops_mcp_server/alibabacloud/utils.py
alibaba_cloud_ops_mcp_server/alibabacloud/static/PROMPT_UNDERSTANDING.md
alibaba_cloud_ops_mcp_server/alibabacloud/static/__init__.py
alibaba_cloud_ops_mcp_server/tools/__init__.py
alibaba_cloud_ops_mcp_server/tools/api_tools.py
alibaba_cloud_ops_mcp_server/tools/application_management_tools.py
alibaba_cloud_ops_mcp_server/tools/cms_tools.py
alibaba_cloud_ops_mcp_server/tools/common_api_tools.py
alibaba_cloud_ops_mcp_server/tools/local_tools.py
alibaba_cloud_ops_mcp_server/tools/oos_tools.py
alibaba_cloud_ops_mcp_server/tools/oss_tools.py
alibaba_cloud_ops_mcp_server-0.9.25.dist-info/METADATA
alibaba_cloud_ops_mcp_server-0.9.25.dist-info/WHEEL
alibaba_cloud_ops_mcp_server-0.9.25.dist-info/entry_points.txt
alibaba_cloud_ops_mcp_server-0.9.25.dist-info/licenses/LICENSE
alibaba_cloud_ops_mcp_server-0.9.25.dist-info/RECORD
