Metadata-Version: 2.4
Name: alibaba-cloud-ops-mcp-server
Version: 0.9.25
Summary: A MCP server for Alibaba Cloud
Author-email: Zheng Dayu <dayu.zdy@alibaba-inc.com>, Zhao Shuaibo <zhaoshuaibo.zsb@alibaba-inc.com>
License-File: LICENSE
Requires-Python: >=3.10
Requires-Dist: alibabacloud-cms20190101>=3.1.4
Requires-Dist: alibabacloud-credentials>=1.0.3
Requires-Dist: alibabacloud-ecs20140526>=6.1.0
Requires-Dist: alibabacloud-oos20190601>=3.5.0
Requires-Dist: alibabacloud-oss-v2>=1.2.0
Requires-Dist: click>=8.1.8
Requires-Dist: fastmcp==2.8.0
Requires-Dist: pydantic==2.11.3
